aws_secretsmanager/__init__.py
aws_secretsmanager/secretsmanager.py
aws_secretsmanager-0.1.1.dist-info/LICENSE
aws_secretsmanager-0.1.1.dist-info/METADATA
aws_secretsmanager-0.1.1.dist-info/WHEEL
aws_secretsmanager-0.1.1.dist-info/top_level.txt
aws_secretsmanager-0.1.1.dist-info/RECORD
